create_package/__init__.py
create_package/__main__.py
create_package/create.py
create_package-1.0.2.dist-info/LICENSE
create_package-1.0.2.dist-info/METADATA
create_package-1.0.2.dist-info/WHEEL
create_package-1.0.2.dist-info/top_level.txt
create_package-1.0.2.dist-info/RECORD
