Metadata-Version: 2.1
Name: create-package
Version: 1.0.2
Summary: A package that makes it easy to create Pypi packages
Home-page: https://github.com/raguiar2/create-python-package
Author: Rui Aguiar
Author-email: raguiar1000@gmail.com
License: UNKNOWN
Platform: UNKNOWN
Classifier: Programming Language :: Python :: 3
Classifier: License :: OSI Approved :: MIT License
Classifier: Operating System :: OS Independent
